{"coord":{"lon":10.5,"lat":51.5},"weather":[{"id":803,"main":"Clouds","description":"broken clouds","icon":"04d"}],"base":"stations","main":{"temp":5.79,"feels_like":3.73,"temp_min":4.35,"temp_max":7.57,"pressure":1021,"humidity":78,"sea_level":1021,"grnd_level":984},"visibility":10000,"wind":{"speed":2.63,"deg":126,"gust":2.9},"clouds":{"all":73},"dt":1637759251,"sys":{"type":2,"id":2039460,"country":"DE","sunrise":1637736669,"sunset":1637767119},"timezone":3600,"id":2921044,"name":"Germany","cod":200}
