{"coord":{"lon":10.5,"lat":51.5},"weather":[{"id":804,"main":"Clouds","description":"overcast clouds","icon":"04d"}],"base":"stations","main":{"temp":8.97,"feels_like":6.4,"temp_min":7.3,"temp_max":10.03,"pressure":1013,"humidity":93,"sea_level":1013,"grnd_level":977},"visibility":10000,"wind":{"speed":4.76,"deg":263,"gust":12.01},"clouds":{"all":100},"dt":1671887113,"sys":{"type":2,"id":74551,"country":"DE","sunrise":1671866552,"sunset":1671894738},"timezone":3600,"id":2921044,"name":"Germany","cod":200}
