{"coord":{"lon":10.5,"lat":51.5},"weather":[{"id":803,"main":"Clouds","description":"broken clouds","icon":"04d"}],"base":"stations","main":{"temp":34.97,"feels_like":35.06,"temp_min":32.75,"temp_max":35.58,"pressure":1011,"humidity":32,"sea_level":1011,"grnd_level":978},"visibility":10000,"wind":{"speed":4.03,"deg":252,"gust":5.81},"clouds":{"all":81},"dt":1659618912,"sys":{"type":2,"id":74551,"country":"DE","sunrise":1659584760,"sunset":1659639730},"timezone":7200,"id":2921044,"name":"Germany","cod":200}
