{"coord":{"lon":10.5,"lat":51.5},"weather":[{"id":804,"main":"Clouds","description":"overcast clouds","icon":"04d"}],"base":"stations","main":{"temp":7.31,"feels_like":4.03,"temp_min":6.19,"temp_max":9.71,"pressure":1011,"humidity":100,"sea_level":1011,"grnd_level":975},"visibility":10000,"wind":{"speed":5.47,"deg":253,"gust":10.41},"clouds":{"all":100},"dt":1671628023,"sys":{"type":2,"id":74551,"country":"DE","sunrise":1671607272,"sunset":1671635444},"timezone":3600,"id":2921044,"name":"Germany","cod":200}
