{"coord":{"lon":10.5,"lat":51.5},"weather":[{"id":800,"main":"Clear","description":"clear sky","icon":"01d"}],"base":"stations","main":{"temp":12.46,"feels_like":10.44,"temp_min":10.08,"temp_max":14.42,"pressure":1018,"humidity":26,"sea_level":1018,"grnd_level":982},"visibility":10000,"wind":{"speed":4.4,"deg":115,"gust":5.51},"clouds":{"all":0},"dt":1647176774,"sys":{"type":2,"id":2039461,"country":"DE","sunrise":1647149829,"sunset":1647191884},"timezone":3600,"id":2921044,"name":"Germany","cod":200}
