{"coord":{"lon":10.5,"lat":51.5},"weather":[{"id":804,"main":"Clouds","description":"overcast clouds","icon":"04d"}],"base":"stations","main":{"temp":8.57,"feels_like":7.45,"temp_min":7.6,"temp_max":10.82,"pressure":1025,"humidity":81,"sea_level":1025,"grnd_level":988},"visibility":10000,"wind":{"speed":2.09,"deg":119,"gust":2.6},"clouds":{"all":100},"dt":1647349680,"sys":{"type":2,"id":2039461,"country":"DE","sunrise":1647322356,"sunset":1647364888},"timezone":3600,"id":2921044,"name":"Germany","cod":200}
