{"coord":{"lon":10.5,"lat":51.5},"weather":[{"id":804,"main":"Clouds","description":"overcast clouds","icon":"04d"}],"base":"stations","main":{"temp":8.37,"feels_like":7.66,"temp_min":7.47,"temp_max":10.59,"pressure":1013,"humidity":95,"sea_level":1013,"grnd_level":977},"visibility":10000,"wind":{"speed":1.62,"deg":278,"gust":2.91},"clouds":{"all":100},"dt":1677157044,"sys":{"type":2,"id":74551,"country":"DE","sunrise":1677133022,"sunset":1677170770},"timezone":3600,"id":2921044,"name":"Germany","cod":200}
