{"coord":{"lon":10.5,"lat":51.5},"weather":[{"id":804,"main":"Clouds","description":"overcast clouds","icon":"04d"}],"base":"stations","main":{"temp":11.41,"feels_like":10.43,"temp_min":11.41,"temp_max":11.41,"pressure":1017,"humidity":70,"sea_level":1017,"grnd_level":981},"visibility":10000,"wind":{"speed":4.74,"deg":20,"gust":6.16},"clouds":{"all":100},"dt":1727960916,"sys":{"type":2,"id":197911,"country":"DE","sunrise":1727932934,"sunset":1727974286},"timezone":7200,"id":2921044,"name":"Germany","cod":200}
