{"coord":{"lon":10.5,"lat":51.5},"weather":[{"id":502,"main":"Rain","description":"heavy intensity rain","icon":"10d"}],"base":"stations","main":{"temp":15.17,"feels_like":15.25,"temp_min":14.14,"temp_max":15.81,"pressure":1010,"humidity":96,"sea_level":1010,"grnd_level":975},"visibility":10000,"wind":{"speed":3.14,"deg":279,"gust":7.61},"rain":{"1h":4.21},"clouds":{"all":100},"dt":1716383083,"sys":{"type":2,"id":197911,"country":"DE","sunrise":1716347786,"sunset":1716405196},"timezone":7200,"id":2921044,"name":"Germany","cod":200}
