{"coord":{"lon":10.5,"lat":51.5},"weather":[{"id":500,"main":"Rain","description":"light rain","icon":"10d"}],"base":"stations","main":{"temp":13,"feels_like":12.6,"temp_min":12.17,"temp_max":13.08,"pressure":1007,"humidity":86,"sea_level":1007,"grnd_level":971},"visibility":10000,"wind":{"speed":7.64,"deg":237,"gust":14.91},"rain":{"1h":0.27},"clouds":{"all":100},"dt":1712235834,"sys":{"type":2,"id":197911,"country":"DE","sunrise":1712205942,"sunset":1712253343},"timezone":7200,"id":2921044,"name":"Germany","cod":200}
