{"coord":{"lon":10.5,"lat":51.5},"weather":[{"id":803,"main":"Clouds","description":"broken clouds","icon":"04d"}],"base":"stations","main":{"temp":15.86,"feels_like":14.81,"temp_min":15.86,"temp_max":15.86,"pressure":1025,"humidity":50,"sea_level":1025,"grnd_level":990},"visibility":10000,"wind":{"speed":8.05,"deg":86,"gust":11},"clouds":{"all":57},"dt":1743599444,"sys":{"type":2,"id":2099722,"country":"DE","sunrise":1743569448,"sunset":1743616317},"timezone":7200,"id":2921044,"name":"Germany","cod":200}
