{"coord":{"lon":10.5,"lat":51.5},"weather":[{"id":801,"main":"Clouds","description":"few clouds","icon":"02d"}],"base":"stations","main":{"temp":18.08,"feels_like":17.33,"temp_min":18.08,"temp_max":18.08,"pressure":1015,"humidity":53,"sea_level":1015,"grnd_level":980},"visibility":10000,"wind":{"speed":5.67,"deg":278,"gust":7.34},"clouds":{"all":18},"dt":1757855163,"sys":{"type":2,"id":2099722,"country":"DE","sunrise":1757825485,"sunset":1757871358},"timezone":7200,"id":2921044,"name":"Germany","cod":200}
